<annotation>
    <folder>SRER</folder>
    <filename>SRER_050.tif</filename>
    <size>
        <width>400</width>
        <height>400</height>
        <depth>3</depth>
    </size>
    <segmented>0</segmented>
    <object>
        <name>Tree</name>
        <pose>Unspecified</pose>
        <truncated>0</truncated>
        <occluded>0</occluded>
        <difficult>0</difficult>
        <bndbox>
            <xmin>166</xmin>
            <ymin>132</ymin>
            <xmax>211</xmax>
            <ymax>182</ymax>
        </bndbox>
    </object>
</annotation>